office31/__init__.py
office31/download.py
office31/split.py
office31-0.1.3.dist-info/LICENSE
office31-0.1.3.dist-info/METADATA
office31-0.1.3.dist-info/WHEEL
office31-0.1.3.dist-info/top_level.txt
office31-0.1.3.dist-info/RECORD
