Metadata-Version: 2.1
Name: office31
Version: 0.1.3
Summary: Revised splits for Office31 domain adaptation experiments
Home-page: https://github.com/LukasHedegaard/office31
Author: Lukas Hedegaard
License: UNKNOWN
Platform: UNKNOWN
Requires-Python: >=3.6
Requires-Dist: datasetops (==0.0.6)
Requires-Dist: requests
Provides-Extra: build
Requires-Dist: setuptools ; extra == 'build'
Requires-Dist: wheel ; extra == 'build'
Requires-Dist: twine ; extra == 'build'
Provides-Extra: tests
Requires-Dist: pytest ; extra == 'tests'
Requires-Dist: pytest-cov ; extra == 'tests'
